{"num":202820,"orderday":"2023-11-02","workday":"2023-12-23","checkstep":"","regist_day":null,"workplacename":"\uc11c\uc6b8 \uc885\ub85c\uad6c \uc0bc\uc120\ubb3c\uc0b0(K20230746-A)","chargedman":"\uae40\uc815\ud6c8","address":"\uc885\ub85c\uad6c \uccad\uc9c4\ub3d9 11-6","firstord":"","firstordman":"\uc774\uc900\uc218","firstordmantel":"","secondord":"TKEK","secondordman":"\ubc15\uc77c\uc6b0\ubd80\uc7a5","secondordmantel":"010-4677-8493","worker":"\ucd94\uc601\ub355","endworkday":"2023-12-21","doneday":"2023-12-23","memo":"5\ub3c4","memo2":"\uacac\uc801 \ucabd\uc7d8 102","chargedmantel":"010-9926-8695","measureday":"2023-12-21","drawday":"2023-12-21","deadline":"2023-12-21","startday":"2023-12-06","testday":"2023-12-27","material1":"","material2":"304 HL 1.2T","material3":"","material4":"","material5":"","material6":"","widejamb":"1","normaljamb":"","smalljamb":"4","update_day":"2023-12-21","delivery":null,"delicar":null,"delicompany":null,"delipay":null,"delimethod":null,"demand":"0000-00-00","hpi":"HD-S-20D-OR","first_writer":"\uc774\ubbf8\ub798 _2023-11-02 10:59:19","update_log":"2023-12-23 15:53:55 - \ucd94\uc601\ub355  2023-12-21 10:48:59 - \uae40\uc740\ube44  2023-12-20 17:01:06 - \uc774\ubbf8\ub798  2023-12-20 16:53:47 - \uc774\ubbf8\ub798  2023-12-20 16:49:37 - \uc774\ubbf8\ub798  2023-12-18 13:28:49 - \uc774\ubbf8\ub798  2023-12-06 09:17:25 - \uc774\ubbf8\ub798  2023-11-29 13:29:16 - \uc774\ubbf8\ub798  2023-11-02 14:06:00 - \uc774\ubbf8\ub798  2023-11-02 11:36:21 - \uc774\ubbf8\ub798  \r\n\r\n\r\n\r\n\r\n\r\n\r\n\r\n&#10&#10","filename1":null,"filename2":null,"checkhold":null,"designer":"\uae40\uc740\ube44","attachment":"","widejambworkfee":"","normaljambworkfee":"","smalljambworkfee":"","workfeedate":"2023-12-29","dwglocation":"\uc11c\uc6b8 \uc885\ub85c\uad6c \uc0bc\uc120\ubb3c\uc0b0 HL \uc640\uc774\ub4dc \ucabd\uc7d8 \ucd94\uc601\ub355\uc18c\uc7a5","work_order":"\uc678\uc8fc","checkmat1":null,"checkmat2":null,"checkmat3":null,"outsourcing":"\uc678\uc8fc","madeconfirm":null,"mymemo":"","assigndate":"2023-12-18","gapcover":""}