{"num":204205,"orderday":"2024-08-21","workday":"0000-00-00","checkstep":"","regist_day":"0000-00-00","workplacename":"\uac15\uc6d0\ub3c4 \uac15\ub989 \uacbd\ud3ec\uc720\uce58\uc6d0(K20240753-A)","chargedman":"","address":"\uac15\uc6d0\ub3c4 \uac15\ub989\uc2dc \uc194\uc62c\ub85c 90.","firstord":"","firstordman":"PM \uae40\uacbd\ub0a8 \ucc28\uc7a5","firstordmantel":"010-5110-3648","secondord":"TKEK","secondordman":"\ubc15\uc77c\uc6b0\ubd80\uc7a5","secondordmantel":"010-4677-8493","worker":"","endworkday":"2024-10-08","doneday":"0000-00-00","memo":"","memo2":"","chargedmantel":"","measureday":"0000-00-00","drawday":"0000-00-00","deadline":"0000-00-00","startday":"2024-09-25","testday":"0000-00-00","material1":"","material2":"HL Ecolor Bronze 1.2T","material3":"","material4":"","material5":"","material6":"","widejamb":"1","normaljamb":"2","smalljamb":"","update_day":null,"delivery":"","delicar":"","delicompany":"","delipay":"","delimethod":"","demand":"0000-00-00","hpi":"HD-S-20D-OR","first_writer":"\uc774\ubbf8\ub798 _2024-08-21 16:13:14","update_log":"2024-08-21 16:41:06 - \uc774\ubbf8\ub798 &#10","filename1":null,"filename2":null,"checkhold":"","designer":" ","attachment":"","widejambworkfee":"","normaljambworkfee":"","smalljambworkfee":"","workfeedate":"0000-00-00","dwglocation":"","work_order":"","checkmat1":"","checkmat2":"","checkmat3":"","outsourcing":"","madeconfirm":"","mymemo":"","assigndate":"0000-00-00","gapcover":"","customer":null}