{"num":204712,"orderday":"2025-02-03","workday":"0000-00-00","checkstep":"","regist_day":"0000-00-00","workplacename":"\uac15\uc6d0\ub3c4 \uc8fc\ubb38\uc9c4 \ub3d9\uba85\uc544\ud30c\ud2b8 (K20250115-A)","chargedman":"\uc774\uc601\ub3c8","address":"\uac15\uc6d0\ub3c4 \uac15\ub989\uc2dc \uc8fc\ubb38\uc9c4\uc74d \ud559\uad501\uae38 9","firstord":"","firstordman":"\uad8c\ubbfc\uc7ac","firstordmantel":"010-2740-8598","secondord":"TKEK","secondordman":"\ubc15\uc77c\uc6b0\ubd80\uc7a5","secondordmantel":"010-4677-8493","worker":"\uc720\uc601","endworkday":"2025-04-04","doneday":"0000-00-00","memo":"\ub3c4\uc77c \ud45c\uba74\ucc98\ub9ac \uc77c\uc8fc\uc77c\uc774\uc0c1\uc18c\uc694 ","memo2":"","chargedmantel":"010-2687-6688","measureday":"2025-03-31","drawday":"2025-04-03","deadline":"0000-00-00","startday":"2025-02-28","testday":"2025-04-17","material1":"\ub3c4\uc77cMTX","material2":"EGI 1.2T","material3":"","material4":"","material5":"","material6":"","widejamb":"1","normaljamb":"","smalljamb":"11","update_day":null,"delivery":"","delicar":"","delicompany":"","delipay":"","delimethod":"","demand":"0000-00-00","hpi":"HD-S-20D-OR","first_writer":"2025-02-03 08:41:04_\ucd5c\uc7a5\uc911 ","update_log":"2025-04-03 14:33:15 - \uc774\uc18c\uc815 2025-04-03 09:27:32 - \ucd5c\uc7a5\uc911 2025-03-31 11:19:24 - \uc720\uc601  2025-03-31 11:19:18 - \uc720\uc601  2025-02-27 08:23:25 - \ucd5c\uc7a5\uc911 2025-02-19 09:22:58 - \ucd5c\uc7a5\uc911 2025-02-19 09:22:28 - \ucd5c\uc7a5\uc911 2025-02-03 09:01:39 - \ucd5c\uc7a5\uc911 2025-02-03 08:49:42 - \ucd5c\uc7a5\uc911 \r\n\r\n\r\n\r\n\r\n\r\n\r\n\r\n&#10","filename1":"2025_03_31_11_19_18_1.jpg","filename2":null,"checkhold":"","designer":"\uc774\uc18c\uc815","attachment":"","widejambworkfee":"","normaljambworkfee":"","smalljambworkfee":"","workfeedate":"0000-00-00","dwglocation":"\uac15\uc6d0\ub3c4 \uc8fc\ubb38\uc9c4 \ub3d9\uba85\uc544\ud30c\ud2b8 \uc640\uc774\ub4dc \ucabd\uc7d8 EGI \uc720\uc601 \uc18c\uc7a5","work_order":"1","checkmat1":"","checkmat2":"","checkmat3":"","outsourcing":"","madeconfirm":"","mymemo":"","assigndate":"2025-02-02","gapcover":"","customer":null}