{"num":203126,"orderday":"2023-12-26","workday":"2024-01-27","checkstep":"","regist_day":null,"workplacename":"\uad11\uc8fc \ud074\ub85c\ubc84\ubaa8\ud154(K20230297-A)","chargedman":"\uc11c\ucc3d\ud638","address":"\uad11\uc8fc \ubd81\uad6c \uc911\ud765\ub85c 83\ubc88\uae38 17-9(\uc2e0\uc548\ub3d9)","firstord":"","firstordman":"PM \uae40\uba85\ud574 \ucc28\uc7a5","firstordmantel":"010-9472-2115","secondord":"TKEK","secondordman":"\ubc15\uc77c\uc6b0\ubd80\uc7a5","secondordmantel":"010-4677-8493","worker":"\uc774\uc778\uc885","endworkday":"2024-01-26","doneday":"2024-01-27","memo":"\uae30\ud0c0\uce35 \uc7ac\uc0ac\uc6a9","memo2":"\uacac\uc801","chargedmantel":"010-4606-1042","measureday":"2024-01-25","drawday":"2024-01-25","deadline":"2024-01-27","startday":"2024-01-17","testday":"2024-02-02","material1":"","material2":"304 HL 1.2T","material3":"","material4":"","material5":"","material6":"","widejamb":"1","normaljamb":"","smalljamb":"","update_day":null,"delivery":null,"delicar":null,"delicompany":null,"delipay":null,"delimethod":null,"demand":"0000-00-00","hpi":"HD-S-20D-OR","first_writer":"\uc774\ubbf8\ub798 _2023-12-26 10:32:10","update_log":"2024-01-27 16:43:13 - \uc774\uc778\uc885  2024-01-27 16:43:00 - \uc774\uc778\uc885  2024-01-25 10:57:12 - \uae40\uc740\ube44 2024-01-08 14:42:21 - \uc774\ubbf8\ub798 2024-01-08 14:41:49 - \uc774\ubbf8\ub798 2023-12-26 10:39:32 - \uc774\ubbf8\ub798 \r\n\r\n\r\n&#10&#10&#10","filename1":"2024_01_27_16_43_00_1.jpg","filename2":"2024_01_27_16_43_01_2.jpg","checkhold":null,"designer":"\uae40\uc740\ube44","attachment":"\ub9c8\uad6c\ub9ac","widejambworkfee":"","normaljambworkfee":"","smalljambworkfee":"","workfeedate":"2024-01-31","dwglocation":"\uad11\uc8fc \ud074\ub85c\ubc84\ubaa8\ud154 HL \uc640\uc774\ub4dc  \uc774\uc778\uc885\uc18c\uc7a5","work_order":"3","checkmat1":null,"checkmat2":null,"checkmat3":null,"outsourcing":null,"madeconfirm":null,"mymemo":"","assigndate":"2024-01-08","gapcover":""}